ap1/__init__.py
ap1/apps.py
ap1/async_safe_requests.py
ap1/db_pack.py
ap1/logger_pack.py
ap1/services_pack.py
ap1/proxy/__init__.py
ap1/proxy/proxy_pack.py
ap1/proxy/proxy_pb2.py
ap1/proxy/proxy_pb2_grpc.py
ap1-0.0.7.dist-info/METADATA
ap1-0.0.7.dist-info/WHEEL
ap1-0.0.7.dist-info/top_level.txt
ap1-0.0.7.dist-info/RECORD
