Metadata-Version: 2.1
Name: ap1
Version: 0.0.7
Summary: Async parser goi
Home-page: https://github.com/Straightholdup/async_parser_app
Author: Askha
Author-email: askhat1008@gmail.com
License: UNKNOWN
Project-URL: Bug Tracker, https://github.com/Straightholdup/async_parser_app/issues
Platform: UNKNOWN
Classifier: Programming Language :: Python :: 3
Classifier: Operating System :: OS Independent
Requires-Python: >=3.6
Requires-Dist: aiohttp (==3.7.4.post0)
Requires-Dist: async-timeout (==3.0.1)
Requires-Dist: attrs (==21.2.0)
Requires-Dist: chardet (==4.0.0)
Requires-Dist: grpcio (==1.41.0)
Requires-Dist: idna (==3.2)
Requires-Dist: multidict (==5.1.0)
Requires-Dist: protobuf (==3.18.0)
Requires-Dist: psycopg2 (==2.9.1)
Requires-Dist: six (==1.16.0)
Requires-Dist: typing-extensions (==3.10.0.2)
Requires-Dist: yarl (==1.6.3)
